MANIFEST.in
README.rst
setup.py
docs/HISTORY.txt
ftw/__init__.py
ftw.slacker.egg-info/PKG-INFO
ftw.slacker.egg-info/SOURCES.txt
ftw.slacker.egg-info/dependency_links.txt
ftw.slacker.egg-info/entry_points.txt
ftw.slacker.egg-info/namespace_packages.txt
ftw.slacker.egg-info/not-zip-safe
ftw.slacker.egg-info/requires.txt
ftw.slacker.egg-info/top_level.txt
ftw/slacker/__init__.py
ftw/slacker/configure.zcml
ftw/slacker/interfaces.py
ftw/slacker/slack_notifier.py
ftw/slacker/testing.py
ftw/slacker/tests/__init__.py
ftw/slacker/tests/test_slack_notifier.py