Metadata-Version: 2.1
Name: ftw.slacker
Version: 1.1.0
Summary: Uses webhooks to post messages into a slack channel.
Home-page: https://git.4teamwork.ch/ftw/ftw.slacker
Author: 4teamwork AG
Author-email: mailto:info@4teamwork.ch
License: GPL2
Keywords: ftw slacker slack webhoock api
Platform: UNKNOWN
Classifier: Development Status :: 6 - Mature
Classifier: Environment :: Web Environment
Classifier: Framework :: Plone :: 4.3
Classifier: Framework :: Plone :: 5.1
Classifier: Framework :: Plone :: 5.2
Classifier: Framework :: Plone :: Addon
Classifier: Framework :: Plone
Classifier: Framework :: Zope :: 2
Classifier: Framework :: Zope :: 4
Classifier: Framework :: Zope
Classifier: Intended Audience :: Developers
Classifier: License :: OSI Approved :: GNU General Public License v2 (GPLv2)
Classifier: Programming Language :: Python :: 2.7
Classifier: Programming Language :: Python :: 3.7
Classifier: Programming Language :: Python
Classifier: Topic :: Software Development :: Libraries :: Python Modules
Provides-Extra: tests
